<?xml version="1.0" encoding="ISO-8859-1" ?>
<?xml-stylesheet type="text/xsl" href="drcss.xsl"?>
<drcreport>
  <header>EvalBoardSandbox</header>
  <drc>
    <status>C:\Microchip\Libero_SoC_v2023.2\Designer/data/drcreport\error.png</status>
    <StatusMessage>Error</StatusMessage>
    <message>Undriven Pin</message>
    <detail>Unconnected input pin DMMainPorts_1:Rx0</detail>
    <crossprobe>liberoaction://cross_probe/smartdesign/EvalBoardSandbox/pins/DMMainPorts_1:Rx0</crossprobe>
  </drc>
</drcreport>
